xplane_airports/AptDat.py
xplane_airports/__init__.py
xplane_airports/_cached_prop.py
xplane_airports/gateway.py
xplane_airports/test_AptDat.py
xplane_airports/test_TaxiRouteNetwork.py
xplane_airports-4.0.1.dist-info/LICENSE
xplane_airports-4.0.1.dist-info/METADATA
xplane_airports-4.0.1.dist-info/WHEEL
xplane_airports-4.0.1.dist-info/top_level.txt
xplane_airports-4.0.1.dist-info/RECORD
