Metadata-Version: 2.1
Name: xplane-airports
Version: 4.0.1
Summary: Tools for manipulating X-Plane's apt.dat files & interfacing with the X-Plane Scenery Gateway
Home-page: https://github.com/X-Plane/xplane_airports
Author: Tyler Young
Author-email: tyler@x-plane.com
License: MIT
Platform: UNKNOWN
Classifier: Programming Language :: Python :: 3
Classifier: Programming Language :: Python :: 3.6
Classifier: Programming Language :: Python :: 3.7
Classifier: License :: OSI Approved :: MIT License
Classifier: Operating System :: OS Independent
Classifier: Development Status :: 4 - Beta
Classifier: Topic :: Games/Entertainment :: Simulation
Requires-Python: >=3.6
Requires-Dist: requests
Requires-Dist: dataclasses (>=0.6) ; python_version < "3.7"
